<nfeProc versao="4.00" xmlns="http://www.portalfiscal.inf.br/nfe"><NFe xmlns="http://www.portalfiscal.inf.br/nfe"><infNFe Id="NFe41240256228356005958550380009487991390387613" versao="4.00"><ide><cUF>41</cUF><cNF>39038761</cNF><natOp>VENDA DE PRODUTOS</natOp><mod>55</mod><serie>38</serie><nNF>948799</nNF><dhEmi>2024-02-01T20:34:20-03:00</dhEmi><dhSaiEnt>2024-02-02T06:00:59-03:00</dhSaiEnt><tpNF>1</tpNF><idDest>1</idDest><cMunFG>4125506</cMunFG><tpImp>2</tpImp><tpEmis>1</tpEmis><cDV>3</cDV><tpAmb>1</tpAmb><finNFe>1</finNFe><indFinal>0</indFinal><indPres>9</indPres><indIntermed>0</indIntermed><procEmi>0</procEmi><verProc>12.02.00.20</verProc></ide><emit><CNPJ>56228356005958</CNPJ><xNome>CRBS SA - CDD Curitiba</xNome><xFant>CDD CURITIBA</xFant><enderEmit><xLgr>Rua Alfredo Pinto</xLgr><nro>29</nro><xBairro>PARQUE DA FONTE</xBairro><cMun>4125506</cMun><xMun>SAO JOSE DOS PINHAIS</xMun><UF>PR</UF><CEP>83065150</CEP><cPais>1058</cPais><xPais>BRASIL</xPais><fone>08007250009</fone></enderEmit><IE>9057987747</IE><IEST>9058248727</IEST><CRT>3</CRT></emit><dest><CNPJ>11788351000125</CNPJ><xNome>ADEMIRO GONCALVES VIEIRA - ACOUGUE</xNome><enderDest><xLgr>EST  GUILHERME WEIGERT</xLgr><nro>1762</nro><xBairro>SANTA CANDIDA</xBairro><cMun>4106902</cMun><xMun>CURITIBA</xMun><UF>PR</UF><CEP>82720000</CEP><cPais>1058</cPais><xPais>BRASIL</xPais><fone>41030306675</fone></enderDest><indIEDest>1</indIEDest><IE>9051631835</IE></dest><autXML><CNPJ>07526557000100</CNPJ></autXML><autXML><CPF>40163494860</CPF></autXML><det nItem="1"><prod><cProd>0018266</cProd><cEAN>7892840800574</cEAN><xProd>PEPSI COLA PET 200ML SH C/12</xProd><NCM>22021000</NCM><CEST>0301001</CEST><indEscala>S</indEscala><CFOP>5403</CFOP><uCom>cx</uCom><qCom>2.0000</qCom><vUnCom>9.8950000000</vUnCom><vProd>19.79</vProd><cEANTrib>7892840800567</cEANTrib><uTrib>un</uTrib><qTrib>24.0000</qTrib><vUnTrib>0.8245833333</vUnTrib><indTot>1</indTot><xPed>135597</xPed><nItemPed>1</nItemPed></prod><imposto><ICMS><ICMS10><orig>0</orig><CST>10</CST><modBC>3</modBC><vBC>19.79</vBC><pICMS>12.00</pICMS><vICMS>2.37</vICMS><modBCST>5</modBCST><vBCST>40.56</vBCST><pICMSST>18.00</pICMSST><vICMSST>4.93</vICMSST><vBCFCPST>40.56</vBCFCPST><pFCPST>2.00</pFCPST><vFCPST>0.81</vFCPST></ICMS10></ICMS><IPI><cEnq>999</cEnq><IPITrib><CST>50</CST><vBC>19.80</vBC><pIPI>1.95</pIPI><vIPI>0.39</vIPI></IPITrib></IPI><PIS><PISAliq><CST>02</CST><vBC>17.42</vBC><pPIS>1.86</pPIS><vPIS>0.32</vPIS></PISAliq></PIS><COFINS><COFINSAliq><CST>02</CST><vBC>17.42</vBC><pCOFINS>8.54</pCOFINS><vCOFINS>1.49</vCOFINS></COFINSAliq></COFINS></imposto><infAdProd>FECOP ST BC :40,56 ALQ:2,00 VL :0,81 Preco Unitario Final:12,9600</infAdProd></det><det nItem="2"><prod><cProd>0008919</cProd><cEAN>7891991002967</cEAN><xProd>GUARANA CHP ANTARCTICA PET 600ML CX12 NPAL</xProd><NCM>22021000</NCM><CEST>0301001</CEST><indEscala>S</indEscala><CFOP>5403</CFOP><uCom>cx</uCom><qCom>1.0000</qCom><vUnCom>27.5900000000</vUnCom><vProd>27.59</vProd><cEANTrib>7891991002646</cEANTrib><uTrib>un</uTrib><qTrib>12.0000</qTrib><vUnTrib>2.2991666667</vUnTrib><indTot>1</indTot><xPed>135597</xPed><nItemPed>2</nItemPed></prod><imposto><ICMS><ICMS10><orig>0</orig><CST>10</CST><modBC>3</modBC><vBC>27.59</vBC><pICMS>12.00</pICMS><vICMS>3.31</vICMS><modBCST>5</modBCST><vBCST>65.04</vBCST><pICMSST>18.00</pICMSST><vICMSST>8.40</vICMSST><vBCFCPST>65.04</vBCFCPST><pFCPST>2.00</pFCPST><vFCPST>1.30</vFCPST></ICMS10></ICMS><IPI><cEnq>999</cEnq><IPITrib><CST>50</CST><vBC>27.59</vBC><pIPI>0.98</pIPI><vIPI>0.27</vIPI></IPITrib></IPI><PIS><PISAliq><CST>02</CST><vBC>24.28</vBC><pPIS>1.86</pPIS><vPIS>0.45</vPIS></PISAliq></PIS><COFINS><COFINSAliq><CST>02</CST><vBC>24.28</vBC><pCOFINS>8.54</pCOFINS><vCOFINS>2.07</vCOFINS></COFINSAliq></COFINS></imposto><infAdProd>FECOP ST BC :65,04 ALQ:2,00 VL :1,30 Preco Unitario Final:37,5600</infAdProd></det><det nItem="3"><prod><cProd>0002349</cProd><cEAN>7891991003148</cEAN><xProd>GUARANA CHP ANTARCTICA PET 2L CAIXA C/6</xProd><NCM>22021000</NCM><CEST>0301001</CEST><indEscala>S</indEscala><CFOP>5403</CFOP><uCom>cx</uCom><qCom>3.0000</qCom><vUnCom>33.9966666667</vUnCom><vProd>101.99</vProd><cEANTrib>7891991001342</cEANTrib><uTrib>un</uTrib><qTrib>18.0000</qTrib><vUnTrib>5.6661111111</vUnTrib><indTot>1</indTot><xPed>135597</xPed><nItemPed>3</nItemPed></prod><imposto><ICMS><ICMS10><orig>0</orig><CST>10</CST><modBC>3</modBC><vBC>101.99</vBC><pICMS>12.00</pICMS><vICMS>12.24</vICMS><modBCST>5</modBCST><vBCST>126.18</vBCST><pICMSST>18.00</pICMSST><vICMSST>10.47</vICMSST><vBCFCPST>126.18</vBCFCPST><pFCPST>2.00</pFCPST><vFCPST>2.52</vFCPST></ICMS10></ICMS><IPI><cEnq>999</cEnq><IPITrib><CST>50</CST><vBC>101.98</vBC><pIPI>0.98</pIPI><vIPI>1.00</vIPI></IPITrib></IPI><PIS><PISAliq><CST>02</CST><vBC>89.75</vBC><pPIS>1.86</pPIS><vPIS>1.67</vPIS></PISAliq></PIS><COFINS><COFINSAliq><CST>02</CST><vBC>89.75</vBC><pCOFINS>8.54</pCOFINS><vCOFINS>7.66</vCOFINS></COFINSAliq></COFINS></imposto><infAdProd>FECOP ST BC :126,18 ALQ:2,00 VL :2,52 Preco Unitario Final:38,6600</infAdProd></det><det nItem="4"><prod><cProd>0018152</cProd><cEAN>7891991014915</cEAN><xProd>GUARANA CHP ANTARCTICA PET 200ML SH C/12</xProd><NCM>22021000</NCM><CEST>0301001</CEST><indEscala>S</indEscala><CFOP>5403</CFOP><uCom>cx</uCom><qCom>1.0000</qCom><vUnCom>11.0500000000</vUnCom><vProd>11.05</vProd><cEANTrib>7891991014908</cEANTrib><uTrib>un</uTrib><qTrib>12.0000</qTrib><vUnTrib>0.9208333333</vUnTrib><indTot>1</indTot><xPed>135597</xPed><nItemPed>4</nItemPed></prod><imposto><ICMS><ICMS10><orig>0</orig><CST>10</CST><modBC>3</modBC><vBC>11.05</vBC><pICMS>12.00</pICMS><vICMS>1.33</vICMS><modBCST>5</modBCST><vBCST>20.40</vBCST><pICMSST>18.00</pICMSST><vICMSST>2.35</vICMSST><vBCFCPST>20.40</vBCFCPST><pFCPST>2.00</pFCPST><vFCPST>0.41</vFCPST></ICMS10></ICMS><IPI><cEnq>999</cEnq><IPITrib><CST>50</CST><vBC>11.06</vBC><pIPI>0.98</pIPI><vIPI>0.11</vIPI></IPITrib></IPI><PIS><PISAliq><CST>02</CST><vBC>9.72</vBC><pPIS>1.86</pPIS><vPIS>0.18</vPIS></PISAliq></PIS><COFINS><COFINSAliq><CST>02</CST><vBC>9.72</vBC><pCOFINS>8.54</pCOFINS><vCOFINS>0.83</vCOFINS></COFINSAliq></COFINS></imposto><infAdProd>FECOP ST BC :20,40 ALQ:2,00 VL :0,41 Preco Unitario Final:13,9200</infAdProd></det><total><ICMSTot><vBC>160.42</vBC><vICMS>19.25</vICMS><vICMSDeson>0.00</vICMSDeson><vFCP>0.00</vFCP><vBCST>252.18</vBCST><vST>26.15</vST><vFCPST>5.04</vFCPST><vFCPSTRet>0.00</vFCPSTRet><vProd>160.42</vProd><vFrete>0.00</vFrete><vSeg>0.00</vSeg><vDesc>0.00</vDesc><vII>0.00</vII><vIPI>1.77</vIPI><vIPIDevol>0.00</vIPIDevol><vPIS>2.62</vPIS><vCOFINS>12.05</vCOFINS><vOutro>0.00</vOutro><vNF>193.38</vNF></ICMSTot></total><transp><modFrete>0</modFrete><transporta><CNPJ>28714218000984</CNPJ><xNome>Zumpy Mobilidade Urbana Sustentavel Ltda</xNome><IE>9096636366</IE><xEnder>RUA Alfredo Pinto                 1405</xEnder><xMun>SAO JOSE DOS PINHAIS</xMun><UF>PR</UF></transporta><veicTransp><placa>CRW7C09</placa><UF>AC</UF></veicTransp><vol><qVol>2</qVol><esp>PC PT200SH12</esp><pesoB>5.280</pesoB></vol><vol><qVol>1</qVol><esp>GCA P60012NP</esp><pesoB>8.200</pesoB></vol><vol><qVol>3</qVol><esp>GCA PT2 CX6</esp><pesoB>38.700</pesoB></vol><vol><qVol>1</qVol><esp>GCA PT200SH12</esp><pesoB>2.640</pesoB></vol></transp><cobr><fat><nFat>948799</nFat><vOrig>193.38</vOrig><vDesc>0.00</vDesc><vLiq>193.38</vLiq></fat><dup><nDup>001</nDup><dVenc>2024-02-02</dVenc><vDup>193.38</vDup></dup></cobr><pag><detPag><indPag>0</indPag><tPag>01</tPag><vPag>193.38</vPag></detPag></pag><infAdic><infCpl>V02V CLIENTE:619-59213-MERC. VIZINHANCA-COD. CORPORATIVO:0$VENDEDOR:203-MATHEUS DOS SANTOS RIBEIRO-MAPA:367983-COND. PAGTO:2-Dinheiro$NUMERO PEDIDO:-ACORDO COMERCIAL:$NOME EMISSOR DE CHEQUES 1:-CNPJ CPF:$NOME DO EMISSOR DE CHEQUES 2:-CNPJ/CPF:$FECOP ST BC :252,18 ALQ:8,00 VL :5,04$RED. BC ST CONF. RE No 6.856/21 E No 7.136/22Dif.Par.conf Art 108 RICMS/12$MS no 5000901-80.2017.4.03.6105             BC ST CONF. NPF No 54/2023$Total PIS:          2,6200  Total COFINS:         12,0500$$$$$$$Red. Aliq. do IPI conf.par. 1o, art. 15 - Lei no 13.097/15. Valor do ICMS excluido da base do PIS/COFINS conforme MS-N. 5000901-80.2017.4.03.6105$$$$$$$$$$$$</infCpl><obsCont xCampo="indTpEntrega"><xTexto>2</xTexto></obsCont><obsCont xCampo="vCte"><xTexto>0.00</xTexto></obsCont></infAdic><infRespTec><CNPJ>81875973000176</CNPJ><xContato>Edgar Alex Hoeltgebaum</xContato><email>edgar.h@ambevtech.com.br</email><fone>47991045442</fone></infRespTec></infNFe><Signature xmlns="http://www.w3.org/2000/09/xmldsig#"><SignedInfo><CanonicalizationMethod Algorithm="http://www.w3.org/TR/2001/REC-xml-c14n-20010315" /><SignatureMethod Algorithm="http://www.w3.org/2000/09/xmldsig#rsa-sha1" /><Reference URI="#NFe41240256228356005958550380009487991390387613"><Transforms><Transform Algorithm="http://www.w3.org/2000/09/xmldsig#enveloped-signature" /><Transform Algorithm="http://www.w3.org/TR/2001/REC-xml-c14n-20010315" /></Transforms><DigestMethod Algorithm="http://www.w3.org/2000/09/xmldsig#sha1" /><DigestValue>e9FuL4q8UYpc4MwaXCV9iKMeOfM=</DigestValue></Reference></SignedInfo><SignatureValue>dG6HwLFx19bAChp7P5cl2svOGmwEAMcUtBlwr7CInzERFTUZomnpfe20VIsqThaSfYXl/wHcXljI
BSgXwhpMSpK5h1euoIpgo0ppZRvptjtSG0u32zV0W1ENuIfqlmxj31WDXH6ausZOEEQzx5gfADeJ
/yauAk4vw7UuOjAX7AFY3San+nOuLB9SZYn4/ojOmwf1sG6BIiOx96iBA/aJpa+Co3JEiHxh1KUn
EPCr1phERPQFTWR6pRf0+C+UKyrdvSTIVKqRZgC1S3YkW68A6WUw/UgT6WbrHaDFts1jckanCtSc
DiFQC9DD9fHWgXaMdAW9ZeYnS2/m8TTkrmVQPA==</SignatureValue><KeyInfo><X509Data><X509Certificate>MIIIDTCCBfWgAwIBAgIQdxUJjeWZYTxVLs1mUg18HTANBgkqhkiG9w0BAQsFADB4MQswCQYDVQQG
EwJCUjETMBEGA1UEChMKSUNQLUJyYXNpbDE2MDQGA1UECxMtU2VjcmV0YXJpYSBkYSBSZWNlaXRh
IEZlZGVyYWwgZG8gQnJhc2lsIC0gUkZCMRwwGgYDVQQDExNBQyBDZXJ0aXNpZ24gUkZCIEc1MB4X
DTIzMDYyMjEyMTM1NFoXDTI0MDYyMTEyMTM1NFowgeoxCzAJBgNVBAYTAkJSMRMwEQYDVQQKDApJ
Q1AtQnJhc2lsMQswCQYDVQQIDAJTUDETMBEGA1UEBwwKSmFndWFyaXVuYTEZMBcGA1UECwwQVmlk
ZW9Db25mZXJlbmNpYTEXMBUGA1UECwwOMDE1NTQyODUwMDAxNzUxNjA0BgNVBAsMLVNlY3JldGFy
aWEgZGEgUmVjZWl0YSBGZWRlcmFsIGRvIEJyYXNpbCAtIFJGQjEWMBQGA1UECwwNUkZCIGUtQ05Q
SiBBMTEgMB4GA1UEAwwXQ1JCUyBTIEE6NTYyMjgzNTYwMDAxMzEwggEiMA0GCSqGSIb3DQEBAQUA
A4IBDwAwggEKAoIBAQCnFdpmTbn3JF0aDEMwpCg9Mr7mMt9I9dFXcfEomNUPcJ2PJZPYmE+ibSYx
YFdD3rVAsRlmIIYy9f4Sbcj+qh6A6fZ0a+6D788YEmftPE6FpDa0B0lx61cCLr+CA2PuC5BJeBN6
MZ8kVX6y0mmVrvkiJk7eFmx97FTbAGTPqSlPC9prPRgwFdv27I7mXL2vzK2FGGdwYbGbC+fdyeBe
6TZZWjEJhA2vFS8F6EiwzNU/kXUtu8ATjuKsLyuw95EDH4lrZeFB6CAvf0L4pjExjkvIERmEJtgb
He+Mv47Wkl/oIaBIZlkLd7pN3ufAv9vT5gYTRRJwlfayoW2we9EL3uYnAgMBAAGjggMeMIIDGjCB
zQYDVR0RBIHFMIHCoD4GBWBMAQMEoDUEMzE2MDQxOTc2MDcyNDAxNDU3ODYwMDAwMDAwMDAwMDAw
MDAwMDAxMDI4Nzk0OFNFQ0NSSqAuBgVgTAEDAqAlBCNFRFVBUkRPIEJSQUdBIENBVkFMQ0FOVEkg
REUgTEFDRVJEQaAZBgVgTAEDA6AQBA41NjIyODM1NjAwMDEzMaAXBgVgTAEDB6AOBAwwMDAwMDAw
MDAwMDCBHG9wc29jaWV0YXJpb2NzY0BhbWJldi5jb20uYnIwCQYDVR0TBAIwADAfBgNVHSMEGDAW
gBRTfX+dvtFh0CC62p/jiacTc1jNQjB/BgNVHSAEeDB2MHQGBmBMAQIBDDBqMGgGCCsGAQUFBwIB
FlxodHRwOi8vaWNwLWJyYXNpbC5jZXJ0aXNpZ24uY29tLmJyL3JlcG9zaXRvcmlvL2RwYy9BQ19D
ZXJ0aXNpZ25fUkZCL0RQQ19BQ19DZXJ0aXNpZ25fUkZCLnBkZjCBvAYDVR0fBIG0MIGxMFegVaBT
hlFodHRwOi8vaWNwLWJyYXNpbC5jZXJ0aXNpZ24uY29tLmJyL3JlcG9zaXRvcmlvL2xjci9BQ0Nl
cnRpc2lnblJGQkc1L0xhdGVzdENSTC5jcmwwVqBUoFKGUGh0dHA6Ly9pY3AtYnJhc2lsLm91dHJh
bGNyLmNvbS5ici9yZXBvc2l0b3Jpby9sY3IvQUNDZXJ0aXNpZ25SRkJHNS9MYXRlc3RDUkwuY3Js
MA4GA1UdDwEB/wQEAwIF4DAdBgNVHSUEFjAUBggrBgEFBQcDAgYIKwYBBQUHAwQwgawGCCsGAQUF
BwEBBIGfMIGcMF8GCCsGAQUFBzAChlNodHRwOi8vaWNwLWJyYXNpbC5jZXJ0aXNpZ24uY29tLmJy
L3JlcG9zaXRvcmlvL2NlcnRpZmljYWRvcy9BQ19DZXJ0aXNpZ25fUkZCX0c1LnA3YzA5BggrBgEF
BQcwAYYtaHR0cDovL29jc3AtYWMtY2VydGlzaWduLXJmYi5jZXJ0aXNpZ24uY29tLmJyMA0GCSqG
SIb3DQEBCwUAA4ICAQAyDo3jedB29XBDOWNnDBxW26s8Cpr9swJfSZ4wwNMXZpF2K2Ph4AhgNjVo
UyETZuIHi6bCV8f9B5rzRScD161X/fAcrx62XI2RPImJiAY/5mLA27xoibx01ca6Y5ycO080oo+q
GndLQiOV/FOiuDxW5u/X/ZlLxRZQ1CODQ1aUzbGRPZyd5J3GwgsVISpUyAAPk6pWWmGzaGSEpWUN
F8UhD41q3gp6aLa0NFvMqfUiYwBDrhrDPOYfhMkHO9g2jSUe4DN6WrZlOs8WwmNPIfbAnzMyZDUE
wEOISbcUU3aP/uZiKX84DvY3N/Jqxw5Pdq+AetiHGdHUwJXLJWRZdypnKfB5XXibk3iFxyHermDp
r+OFeupdueSVyxNXhPBIPwDmtreIUlmIyNbcRXrjm9wJj0aAZ5C6enfWptxIyvwfIGappbyEHbaC
CXjWo5uqyRjlYkqvNSFU+QowUiKq5/k04oDr5l6B24rxQohOjsrxWmPgvQRPuc8tgfgNObDlp/6m
V+34CoRKZ/E4bPgtFMzy8k3ucpPgBdd+1RiVIqaYHWXlIeu+TOW7zhpGQPoZ90po22dznl6kYvNg
rwH1hazDfZYaPS11eitOWXhZy20oqL4G4Bphn/Xe6Ld0D+QXImD4BkCfynxbfcPqzxpWkh8f6e46
rXvXoYFQf3jeMmJ9Cw==</X509Certificate></X509Data></KeyInfo></Signature></NFe><protNFe versao="4.00"><infProt Id="ID141240032781963"><tpAmb>1</tpAmb><verAplic>PR-v4_8_35</verAplic><chNFe>41240256228356005958550380009487991390387613</chNFe><dhRecbto>2024-02-01T20:34:28-03:00</dhRecbto><nProt>141240032781963</nProt><digVal>e9FuL4q8UYpc4MwaXCV9iKMeOfM=</digVal><cStat>100</cStat><xMotivo>Autorizado o uso da NF-e</xMotivo></infProt></protNFe></nfeProc>